pysup/__init__.py
pysup/support.py
pysup-0.1.19.dist-info/LICENSE
pysup-0.1.19.dist-info/METADATA
pysup-0.1.19.dist-info/WHEEL
pysup-0.1.19.dist-info/RECORD
